guided_filter_tf/__init__.py
guided_filter_tf/box_filter.py
guided_filter_tf/guided_filter.py
guided_filter_tf-1.1.1.dist-info/DESCRIPTION.rst
guided_filter_tf-1.1.1.dist-info/METADATA
guided_filter_tf-1.1.1.dist-info/RECORD
guided_filter_tf-1.1.1.dist-info/WHEEL
guided_filter_tf-1.1.1.dist-info/metadata.json
guided_filter_tf-1.1.1.dist-info/top_level.txt
guided_filter_tf-1.1.1.dist-info/zip-safe
