Metadata-Version: 2.0
Name: guided-filter-tf
Version: 1.1.1
Summary: Deep Guided Filtering Layer for TensorFlow
Home-page: https://github.com/wuhuikai/DeepGuidedFilter
Author: wuhuikai
Author-email: huikaiwu@icloud.com
License: UNKNOWN
Platform: UNKNOWN
